pasteplayer.py
pasteplayer-1.3.dist-info/DESCRIPTION.rst
pasteplayer-1.3.dist-info/METADATA
pasteplayer-1.3.dist-info/RECORD
pasteplayer-1.3.dist-info/WHEEL
pasteplayer-1.3.dist-info/entry_points.txt
pasteplayer-1.3.dist-info/metadata.json
pasteplayer-1.3.dist-info/top_level.txt
