Metadata-Version: 2.0
Name: pasteplayer
Version: 1.3
Summary: A thin mpv wrapper for on-the-fly playlist editing
Home-page: https://github.com/leftshift/pasteplayer
Author: uberardy
Author-email: github@ardy.io
License: GPLv3
Platform: UNKNOWN
Requires-Dist: python-mpv
